xian_tools/encoding.py
xian_tools/formating.py
xian_tools/transactions.py
xian_tools/utils.py
xian_tools/wallet.py
xian_tools/xian.py
xian_tools/xian_datetime.py
xian_tools/xian_decimal.py
xian_tools-0.9.20.dist-info/METADATA
xian_tools-0.9.20.dist-info/WHEEL
xian_tools-0.9.20.dist-info/RECORD
