Metadata-Version: 2.1
Name: xian-tools
Version: 0.9.20
Summary: Core utils to interact with Xian network
Author: endogen
Requires-Python: >=3.9,<4.0
Classifier: Programming Language :: Python :: 3
Classifier: Programming Language :: Python :: 3.9
Classifier: Programming Language :: Python :: 3.10
Classifier: Programming Language :: Python :: 3.11
Classifier: Programming Language :: Python :: 3.12
Requires-Dist: pynacl (>=1.5.0,<2.0.0)
Requires-Dist: requests (>=2.31.0,<3.0.0)
